netrias_client/__init__.py
netrias_client/_adapter.py
netrias_client/_async_utils.py
netrias_client/_client.py
netrias_client/_config.py
netrias_client/_core.py
netrias_client/_data_model_store.py
netrias_client/_discovery.py
netrias_client/_errors.py
netrias_client/_gateway_bypass.py
netrias_client/_http.py
netrias_client/_io.py
netrias_client/_logging.py
netrias_client/_models.py
netrias_client/_sfn_discovery.py
netrias_client/_validators.py
netrias_client/scripts.py
netrias_client-0.2.2.dist-info/METADATA
netrias_client-0.2.2.dist-info/WHEEL
netrias_client-0.2.2.dist-info/entry_points.txt
netrias_client-0.2.2.dist-info/licenses/LICENSE
netrias_client-0.2.2.dist-info/RECORD
