Metadata-Version: 2.4
Name: netrias_client
Version: 0.2.2
Summary: Python client for the Netrias harmonization API
Project-URL: Homepage, https://github.com/netrias/netrias_client
Project-URL: Repository, https://github.com/netrias/netrias_client
Project-URL: Documentation, https://github.com/netrias/netrias_client#readme
Author-email: Chris Harman <charman@netrias.com>
License: MIT License
License-File: LICENSE
Keywords: api,cde,client,harmonization,netrias
Classifier: Intended Audience :: Developers
Classifier: License :: OSI Approved :: MIT License
Classifier: Operating System :: OS Independent
Classifier: Programming Language :: Python :: 3
Classifier: Programming Language :: Python :: 3 :: Only
Classifier: Programming Language :: Python :: 3.10
Classifier: Programming Language :: Python :: 3.11
Classifier: Programming Language :: Python :: 3.12
Requires-Python: >=3.10
Requires-Dist: boto3
Requires-Dist: httpx
Provides-Extra: dev
Requires-Dist: basedpyright; extra == 'dev'
Requires-Dist: pytest-asyncio>=0.23; extra == 'dev'
Requires-Dist: pytest>=7; extra == 'dev'
Requires-Dist: python-dotenv>=1.0; extra == 'dev'
Requires-Dist: ruff>=0.5.0; extra == 'dev'
Requires-Dist: twine>=5.0; extra == 'dev'
Requires-Dist: ty; extra == 'dev'
Requires-Dist: typing-extensions; extra == 'dev'
